verify_vat_number/__init__.py
verify_vat_number/ares.py
verify_vat_number/data.py
verify_vat_number/exceptions.py
verify_vat_number/py.typed
verify_vat_number/utils.py
verify_vat_number/vies.py
verify_vat_number/tests/__init__.py
verify_vat_number/tests/test_ares.py
verify_vat_number/tests/test_utils.py
verify_vat_number/tests/test_vies.py
verify_vat_number/tests/utils.py
verify_vat_number/tests/vies-checkVatService.wsdl
verify_vat_number/tests/data/ares_basic_67985726.json
verify_vat_number/tests/data/ares_vr_14347890.json
verify_vat_number/tests/data/ares_vr_67985726.json
verify_vat_number-2.0.0.dist-info/METADATA
verify_vat_number-2.0.0.dist-info/WHEEL
verify_vat_number-2.0.0.dist-info/top_level.txt
verify_vat_number-2.0.0.dist-info/RECORD
