Metadata-Version: 2.1
Name: verify-vat-number
Version: 2.0.0
Summary: Verify VAT number by ARES/VIES
Home-page: https://gitlab.nic.cz/utils/verify-vat-number/
Author: Zdeněk Böhm
Author-email: zdenek.bohm@nic.cz
License: GPLv3+
Classifier: Typing :: Typed
Classifier: Programming Language :: Python
Classifier: Programming Language :: Python :: 3.8
Classifier: Programming Language :: Python :: 3.9
Classifier: Programming Language :: Python :: 3.10
Requires-Python: ~=3.8
Requires-Dist: zeep >=3.3.1
Provides-Extra: quality
Requires-Dist: doc8 ; extra == 'quality'
Requires-Dist: flake8 ; extra == 'quality'
Requires-Dist: isort ; extra == 'quality'
Requires-Dist: mypy ; extra == 'quality'
Requires-Dist: pydocstyle ; extra == 'quality'
Provides-Extra: test
Requires-Dist: responses ; extra == 'test'
Requires-Dist: freezegun ; extra == 'test'
Provides-Extra: types
Requires-Dist: types-requests ; extra == 'types'
Requires-Dist: types-freezegun ; extra == 'types'
